pylimit/__init__.py
pylimit/pyratelimit.py
pylimit/pyratelimit_exception.py
pylimit/redis_helper.py
pylimit-1.0.0.dist-info/LICENSE.txt
pylimit-1.0.0.dist-info/METADATA
pylimit-1.0.0.dist-info/WHEEL
pylimit-1.0.0.dist-info/top_level.txt
pylimit-1.0.0.dist-info/RECORD
